pure_db_uzb-0.1.0.dist-info/licenses/LICENCE
puredb/__init__.py
pure_db_uzb-0.1.0.dist-info/METADATA
pure_db_uzb-0.1.0.dist-info/WHEEL
pure_db_uzb-0.1.0.dist-info/top_level.txt
pure_db_uzb-0.1.0.dist-info/RECORD
