Metadata-Version: 2.4
Name: pure-db-uzb
Version: 0.1.0
Summary: Oddiy faylga asoslangan va serverga ulanadigan yani global ma'lumotlarni saqlay oladigan ma'lumotlar bazasi
Author: Salohiddin
Author-email: salohiddinsalohiddin123@gmail.com
Classifier: Programming Language :: Python :: 3
Classifier: License :: OSI Approved :: MIT License
Classifier: Operating System :: OS Independent
Requires-Python: >=3.6
License-File: LICENCE
Requires-Dist: requests
Dynamic: author
Dynamic: author-email
Dynamic: classifier
Dynamic: description
Dynamic: description-content-type
Dynamic: license-file
Dynamic: requires-dist
Dynamic: requires-python
Dynamic: summary
